AUTHORS.rst
CONTRIBUTING.rst
HISTORY.rst
LICENSE
MANIFEST.in
README.rst
setup.cfg
setup.py
docs/Makefile
docs/authors.rst
docs/conf.py
docs/contributing.rst
docs/history.rst
docs/index.rst
docs/installation.rst
docs/make.bat
docs/modules.rst
docs/readme.rst
docs/usage.rst
docs/validatorpy.rst
docs/_build/html/_static/ajax-loader.gif
docs/_build/html/_static/comment-bright.png
docs/_build/html/_static/comment-close.png
docs/_build/html/_static/comment.png
docs/_build/html/_static/down-pressed.png
docs/_build/html/_static/down.png
docs/_build/html/_static/file.png
docs/_build/html/_static/minus.png
docs/_build/html/_static/plus.png
docs/_build/html/_static/up-pressed.png
docs/_build/html/_static/up.png
tests/test_validatorpy.py
validatorpy/__init__.py
validatorpy/cli.py
validatorpy/validatorpy.py
validatorpy.egg-info/PKG-INFO
validatorpy.egg-info/SOURCES.txt
validatorpy.egg-info/dependency_links.txt
validatorpy.egg-info/entry_points.txt
validatorpy.egg-info/not-zip-safe
validatorpy.egg-info/requires.txt
validatorpy.egg-info/top_level.txt