Metadata-Version: 1.1
Name: validatorpy
Version: 0.1.0
Summary: Performs basic validations of data types
Home-page: https://github.com/ssaldarriaga/validatorpy
Author: Sebastian Saldarriaga
Author-email: sebas@ubidots.com
License: MIT license
Keywords: validatorpy
Platform: UNKNOWN
Classifier: Development Status :: 2 - Pre-Alpha
Classifier: Intended Audience :: Developers
Classifier: License :: OSI Approved :: MIT License
Classifier: Natural Language :: English
Classifier: Programming Language :: Python :: 2
Classifier: Programming Language :: Python :: 2.7
Classifier: Programming Language :: Python :: 3
Classifier: Programming Language :: Python :: 3.4
Classifier: Programming Language :: Python :: 3.5
Classifier: Programming Language :: Python :: 3.6
